generals/__init__.py
generals/agents/__init__.py
generals/agents/agent.py
generals/agents/expander_agent.py
generals/agents/random_agent.py
generals/assets/__init__.py
generals/assets/fonts/OFL.txt
generals/assets/fonts/Quicksand-Bold.ttf
generals/assets/fonts/Quicksand-Light.ttf
generals/assets/fonts/Quicksand-Medium.ttf
generals/assets/fonts/Quicksand-Regular.ttf
generals/assets/fonts/Quicksand-SemiBold.ttf
generals/assets/fonts/Quicksand-VariableFont_wght.ttf
generals/assets/fonts/Quicksand.zip
generals/assets/fonts/README.txt
generals/assets/fonts/__init__.py
generals/assets/gifs/wide_gameplay.gif
generals/assets/gifs/wider_gameplay.gif
generals/assets/images/__init__.py
generals/assets/images/citie.png
generals/assets/images/city.png
generals/assets/images/crown.png
generals/assets/images/crownie.png
generals/assets/images/mountain.png
generals/assets/images/mountainie.png
generals/assets/images/preview.png
generals/assets/images/test.png
generals/core/__init__.py
generals/core/action.py
generals/core/channels.py
generals/core/config.py
generals/core/game.py
generals/core/grid.py
generals/core/observation.py
generals/core/replay.py
generals/core/rewards.py
generals/envs/__init__.py
generals/envs/gymnasium_generals.py
generals/envs/pettingzoo_generals.py
generals/gui/__init__.py
generals/gui/event_handler.py
generals/gui/gui.py
generals/gui/properties.py
generals/gui/rendering.py
generals/remote/__init__.py
generals/remote/generalsio_client.py
generals/remote/generalsio_state.py
generals_bots-2.5.0.dist-info/LICENSE
generals_bots-2.5.0.dist-info/METADATA
generals_bots-2.5.0.dist-info/WHEEL
generals_bots-2.5.0.dist-info/RECORD
