Metadata-Version: 2.1
Name: generals-bots
Version: 2.5.0
Summary: Develop your agent for generals.io!
License: MIT
Author: Matej Straka
Author-email: strakammm@gmail.com
Requires-Python: >=3.11,<4.0
Classifier: License :: OSI Approved :: MIT License
Classifier: Programming Language :: Python :: 3
Classifier: Programming Language :: Python :: 3.11
Classifier: Programming Language :: Python :: 3.12
Classifier: Programming Language :: Python :: 3.13
Requires-Dist: gymnasium (>=1.0.0,<2.0.0)
Requires-Dist: numba (>=0.61.0,<0.62.0)
Requires-Dist: numpy (>=2.1.1,<3.0.0)
Requires-Dist: pettingzoo (>=1.24.3,<2.0.0)
Requires-Dist: pygame (>=2.6.0,<3.0.0)
Requires-Dist: python-socketio[client] (>=5.11.4,<6.0.0)
Requires-Dist: scipy (>=1.14.1,<2.0.0)
